MANIFEST.in
README.md
setup.py
version.txt
dubbo_client/__init__.py
dubbo_client/common.py
dubbo_client/config.py
dubbo_client/registry.py
dubbo_client/rpcerror.py
dubbo_client/rpclib.py
dubbo_client.egg-info/PKG-INFO
dubbo_client.egg-info/SOURCES.txt
dubbo_client.egg-info/dependency_links.txt
dubbo_client.egg-info/requires.txt
dubbo_client.egg-info/top_level.txt
tests/__init__.py
tests/test_config.py
tests/test_performance.py
tests/test_rawclient.py
tests/test_registry.py
tests/test_rpclib.py