Metadata-Version: 1.1
Name: dubbo-client
Version: 1.0.0b5
Summary: Python Dubbo Client
Home-page: https://github.com/ofpay/dubbo-client-py
Author: Joe Cao
Author-email: chinalibra@gmail.com
License: UNKNOWN
Download-URL: https://github.com/ofpay/dubbo-client-py/raw/master/dist/dubbo-client-1.0.0b5-py2.7.egg
Keywords: Dubbo,JSON-RPC,JSON,RPC,Client,HTTP-Client,Remote Procedure Call,JavaScript Object Notation,
Platform: UNKNOWN
Classifier: Development Status :: 4 - Beta
Classifier: Environment :: Web Environment
Classifier: Intended Audience :: Developers
Classifier: License :: OSI Approved :: MIT License
Classifier: Operating System :: OS Independent
Classifier: Programming Language :: Python :: 2
Classifier: Topic :: Software Development :: Libraries :: Python Modules
Classifier: Topic :: Communications
Classifier: Topic :: System :: Networking
Classifier: Topic :: Internet :: WWW/HTTP
Classifier: Topic :: Internet :: WWW/HTTP :: HTTP Servers
Classifier: Topic :: Internet :: WWW/HTTP :: WSGI :: Application
